{
    "type": "list",
    "headline": "Live Tv",
    "template": {
        "type": "separate",
        "layout": "0,0,2,3"
    },
    "items": [
        {
            "type": "teaser",
            "color": "msx-white",
            "image": "https://infinitytechcmp.github.io/msx/data/base/tv-json/live/And_Pictures.png",
            "imageFiller": "width-center",
            "action": "video:plugin:http://msx.benzac.de/plugins/hls.html?url=http://vo01.mohdtv.com:8880/live/voby5038/67747551/1964.m3u8"
        },
        {
            "type": "teaser",
            "color": "msx-white",
            "image": "https://infinitytechcmp.github.io/msx/data/base/tv-json/live/And_TV.png",
            "imageFiller": "width-center",
            "action": "video:plugin:http://msx.benzac.de/plugins/hls.html?url=http://vo01.mohdtv.com:8880/live/voby5038/67747551/1962.m3u8"
        },
        {
            "type": "teaser",
            "color": "msx-white",
            "image": "https://infinitytechcmp.github.io/msx/data/base/tv-json/live/And_Prive_HD.png",
            "imageFiller": "width-center",
            "action": "video:plugin:http://msx.benzac.de/plugins/hls.html?url=http://vo01.mohdtv.com:8880/live/voby5038/67747551/1963.m3u8"
        },
        {
            "type": "teaser",
            "color": "msx-white",
            "image": "https://infinitytechcmp.github.io/msx/data/base/tv-json/live/9X_JALWA.png",
            "imageFiller": "width-center",
            "action": "video:plugin:http://msx.benzac.de/plugins/hls.html?url=http://vo01.mohdtv.com:8880/live/voby5038/67747551/1958.m3u8"
        },
        {
            "type": "teaser",
            "color": "msx-white",
            "image": "https://infinitytechcmp.github.io/msx/data/base/tv-json/live/9X_JHAKAAS.png",
            "imageFiller": "width-center",
            "action": "video:plugin:http://msx.benzac.de/plugins/hls.html?url=http://vo01.mohdtv.com:8880/live/voby5038/67747551/1957.m3u8"
        },
        {
            "type": "teaser",
            "color": "msx-white",
            "image": "https://infinitytechcmp.github.io/msx/data/base/tv-json/live/9XM.png",
            "imageFiller": "width-center",
            "action": "video:plugin:http://msx.benzac.de/plugins/hls.html?url=http://vo01.mohdtv.com:8880/live/voby5038/67747551/1954.m3u8"
        },
        {
            "type": "teaser",
            "color": "msx-white",
            "image": "https://infinitytechcmp.github.io/msx/data/base/tv-json/live/AAJ_TAK.png",
            "imageFiller": "width-center",
            "action": "video:plugin:http://msx.benzac.de/plugins/hls.html?url=http://vo01.mohdtv.com:8880/live/voby5038/67747551/1953.m3u8"
        },
        {
            "type": "teaser",
            "color": "msx-white",
            "image": "https://infinitytechcmp.github.io/msx/data/base/tv-json/live/ABP_NEWS.png",
            "imageFiller": "width-center",
            "action": "video:plugin:http://msx.benzac.de/plugins/hls.html?url=http://vo01.mohdtv.com:8880/live/voby5038/67747551/1949.m3u8"
        },
        {
            "type": "teaser",
            "color": "msx-white",
            "image": "https://infinitytechcmp.github.io/msx/data/base/tv-json/live/B4U_MUSIC.png",
            "imageFiller": "width-center",
            "action": "video:plugin:http://msx.benzac.de/plugins/hls.html?url=http://vo01.mohdtv.com:8880/live/voby5038/67747551/1944.m3u8"
        },
        {
            "type": "teaser",
            "color": "msx-white",
            "image": "https://infinitytechcmp.github.io/msx/data/base/tv-json/live/B4U_KADAK.png",
            "imageFiller": "width-center",
            "action": "video:plugin:http://msx.benzac.de/plugins/hls.html?url=http://vo01.mohdtv.com:8880/live/voby5038/67747551/1943.m3u8"
        },
        {
            "type": "teaser",
            "color": "msx-white",
            "image": "https://infinitytechcmp.github.io/msx/data/base/tv-json/live/B4U_MOVIES.png",
            "imageFiller": "width-center",
            "action": "video:plugin:http://msx.benzac.de/plugins/hls.html?url=http://vo01.mohdtv.com:8880/live/voby5038/67747551/1942.m3u8"
        },
        {
            "type": "teaser",
            "color": "msx-white",
            "image": "https://infinitytechcmp.github.io/msx/data/base/tv-json/live/COLORS.png",
            "imageFiller": "width-center",
            "action": "video:plugin:http://msx.benzac.de/plugins/hls.html?url=http://vo01.mohdtv.com:8880/live/voby5038/67747551/1931.m3u8"
        },
        {
            "type": "teaser",
            "color": "msx-white",
            "image": "https://infinitytechcmp.github.io/msx/data/base/tv-json/live/COLORS_CINEPLEX.png",
            "imageFiller": "width-center",
            "action": "video:plugin:http://msx.benzac.de/plugins/hls.html?url=http://vo01.mohdtv.com:8880/live/voby5038/67747551/1929.m3u8"
        },
        {
            "type": "teaser",
            "color": "msx-white",
            "image": "https://infinitytechcmp.github.io/msx/data/base/tv-json/live/COLORS_MARATHI.png",
            "imageFiller": "width-center",
            "action": "video:plugin:http://msx.benzac.de/plugins/hls.html?url=http://vo01.mohdtv.com:8880/live/voby5038/67747551/1925.m3u8"
        },
        {
            "type": "teaser",
            "color": "msx-white",
            "image": "https://infinitytechcmp.github.io/msx/data/base/tv-json/live/NDTV_24X7.png",
            "imageFiller": "width-center",
            "action": "video:plugin:http://msx.benzac.de/plugins/hls.html?url=http://vo01.mohdtv.com:8880/live/voby5038/67747551/55358.m3u8"
        },
        {
            "type": "teaser",
            "color": "msx-white",
            "image": "https://infinitytechcmp.github.io/msx/data/base/tv-json/live/Nick_Junior.png",
            "imageFiller": "width-center",
            "action": "video:plugin:http://msx.benzac.de/plugins/hls.html?url=http://vo01.mohdtv.com:8880/live/voby5038/67747551/55345.m3u8"
        },
        {
            "type": "teaser",
            "color": "msx-white",
            "image": "https://infinitytechcmp.github.io/msx/data/base/tv-json/live/SONY.png",
            "imageFiller": "width-center",
            "action": "video:plugin:http://msx.benzac.de/plugins/hls.html?url=http://vo01.mohdtv.com:8880/live/voby5038/67747551/55296.m3u8"
        },
        {
            "type": "teaser",
            "color": "msx-white",
            "image": "https://infinitytechcmp.github.io/msx/data/base/tv-json/live/Sony_SAB.png",
            "imageFiller": "width-center",
            "action": "video:plugin:http://msx.benzac.de/plugins/hls.html?url=http://vo01.mohdtv.com:8880/live/voby5038/67747551/55290.m3u8"
        },
        {
            "type": "teaser",
            "color": "msx-white",
            "image": "https://infinitytechcmp.github.io/msx/data/base/tv-json/live/SONY_SAB_UK.png",
            "imageFiller": "width-center",
            "action": "video:plugin:http://msx.benzac.de/plugins/hls.html?url=http://vo01.mohdtv.com:8880/live/voby5038/67747551/55289.m3u8"
        },
        {
            "type": "teaser",
            "color": "msx-white",
            "image": "https://infinitytechcmp.github.io/msx/data/base/tv-json/live/SONY_TEN_1.png",
            "imageFiller": "width-center",
            "action": "video:plugin:http://msx.benzac.de/plugins/hls.html?url=http://vo01.mohdtv.com:8880/live/voby5038/67747551/55284.m3u8"
        },
        {
            "type": "teaser",
            "color": "msx-white",
            "image": "https://infinitytechcmp.github.io/msx/data/base/tv-json/live/Sony_Ten_3.png",
            "imageFiller": "width-center",
            "action": "video:plugin:http://msx.benzac.de/plugins/hls.html?url=http://vo01.mohdtv.com:8880/live/voby5038/67747551/55281.m3u8"
        },
        {
            "type": "teaser",
            "color": "msx-white",
            "image": "https://infinitytechcmp.github.io/msx/data/base/tv-json/live/SONY_TV_ASIA.png",
            "imageFiller": "width-center",
            "action": "video:plugin:http://msx.benzac.de/plugins/hls.html?url=http://vo01.mohdtv.com:8880/live/voby5038/67747551/55280.m3u8"
        },
        {
            "type": "teaser",
            "color": "msx-white",
            "image": "https://infinitytechcmp.github.io/msx/data/base/tv-json/live/Sony_TV_UK.png",
            "imageFiller": "width-center",
            "action": "video:plugin:http://msx.benzac.de/plugins/hls.html?url=http://vo01.mohdtv.com:8880/live/voby5038/67747551/55279.m3u8"
        },
        {
            "type": "teaser",
            "color": "msx-white",
            "image": "https://infinitytechcmp.github.io/msx/data/base/tv-json/live/STAR_PLUS.png",
            "imageFiller": "width-center",
            "action": "video:plugin:http://msx.benzac.de/plugins/hls.html?url=http://vo01.mohdtv.com:8880/live/voby5038/67747551/55274.m3u8"
        },
        {
            "type": "teaser",
            "color": "msx-white",
            "image": "https://infinitytechcmp.github.io/msx/data/base/tv-json/live/STAR_SPORTS_1.png",
            "imageFiller": "width-center",
            "action": "video:plugin:http://msx.benzac.de/plugins/hls.html?url=http://vo01.mohdtv.com:8880/live/voby5038/67747551/55273.m3u8"
        },
        {
            "type": "teaser",
            "color": "msx-white",
            "image": "https://infinitytechcmp.github.io/msx/data/base/tv-json/live/STAR_SPORTS_2.png",
            "imageFiller": "width-center",
            "action": "video:plugin:http://msx.benzac.de/plugins/hls.html?url=http://vo01.mohdtv.com:8880/live/voby5038/67747551/55272.m3u8"
        },
        {
            "type": "teaser",
            "color": "msx-white",
            "image": "https://infinitytechcmp.github.io/msx/data/base/tv-json/live/STAR_SPORTS_3.png",
            "imageFiller": "width-center",
            "action": "video:plugin:http://msx.benzac.de/plugins/hls.html?url=http://vo01.mohdtv.com:8880/live/voby5038/67747551/55271.m3u8"
        },
        {
            "type": "teaser",
            "color": "msx-white",
            "image": "https://infinitytechcmp.github.io/msx/data/base/tv-json/live/STAR_SPORTS_SELECT_1.jpg",
            "imageFiller": "width-center",
            "action": "video:plugin:http://msx.benzac.de/plugins/hls.html?url=http://vo01.mohdtv.com:8880/live/voby5038/67747551/55270.m3u8"
        },
        {
            "type": "teaser",
            "color": "msx-white",
            "image": "https://infinitytechcmp.github.io/msx/data/base/tv-json/live/STAR_SPORTS_SELECT_2.png",
            "imageFiller": "width-center",
            "action": "video:plugin:http://msx.benzac.de/plugins/hls.html?url=http://vo01.mohdtv.com:8880/live/voby5038/67747551/55269.m3u8"
        },
        {
            "type": "teaser",
            "color": "msx-white",
            "image": "https://infinitytechcmp.github.io/msx/data/base/tv-json/live/SONY_MAX.png",
            "imageFiller": "width-center",
            "action": "video:plugin:http://msx.benzac.de/plugins/hls.html?url=http://vo01.mohdtv.com:8880/live/voby5038/67747551/55268.m3u8"
        },
        {
            "type": "teaser",
            "color": "msx-white",
            "image": "https://infinitytechcmp.github.io/msx/data/base/tv-json/live/SONY_MAX_2.png",
            "imageFiller": "width-center",
            "action": "video:plugin:http://msx.benzac.de/plugins/hls.html?url=http://vo01.mohdtv.com:8880/live/voby5038/67747551/55264.m3u8"
        },
        {
            "type": "teaser",
            "color": "msx-white",
            "image": "https://infinitytechcmp.github.io/msx/data/base/tv-json/live/SONY_PAL.png",
            "imageFiller": "width-center",
            "action": "video:plugin:http://msx.benzac.de/plugins/hls.html?url=http://vo01.mohdtv.com:8880/live/voby5038/67747551/55262.m3u8"
        },
        {
            "type": "teaser",
            "color": "msx-white",
            "image": "https://infinitytechcmp.github.io/msx/data/base/tv-json/live/STAR_BHARAT.jpg",
            "imageFiller": "width-center",
            "action": "video:plugin:http://msx.benzac.de/plugins/hls.html?url=http://vo01.mohdtv.com:8880/live/voby5038/67747551/55258.m3u8"
        },
        {
            "type": "teaser",
            "color": "msx-white",
            "image": "https://infinitytechcmp.github.io/msx/data/base/tv-json/live/Star_Gold.svg",
            "imageFiller": "width-center",
            "action": "video:plugin:http://msx.benzac.de/plugins/hls.html?url=http://vo01.mohdtv.com:8880/live/voby5038/67747551/55257.m3u8"
        },
        {
            "type": "teaser",
            "color": "msx-white",
            "image": "https://infinitytechcmp.github.io/msx/data/base/tv-json/live/STAR_GOLD_SELECT.",
            "imageFiller": "width-center",
            "action": "video:plugin:http://msx.benzac.de/plugins/hls.html?url=http://vo01.mohdtv.com:8880/live/voby5038/67747551/55256.m3u8"
        },
        {
            "type": "teaser",
            "color": "msx-white",
            "image": "https://infinitytechcmp.github.io/msx/data/base/tv-json/live/ZEE_BOLLYWOOD.png",
            "imageFiller": "width-center",
            "action": "video:plugin:http://msx.benzac.de/plugins/hls.html?url=http://vo01.mohdtv.com:8880/live/voby5038/67747551/55212.m3u8"
        },
        {
            "type": "teaser",
            "color": "msx-white",
            "image": "https://infinitytechcmp.github.io/msx/data/base/tv-json/live/ZEE_CINEMA.png",
            "imageFiller": "width-center",
            "action": "video:plugin:http://msx.benzac.de/plugins/hls.html?url=http://vo01.mohdtv.com:8880/live/voby5038/67747551/55210.m3u8"
        },
        {
            "type": "teaser",
            "color": "msx-white",
            "image": "https://infinitytechcmp.github.io/msx/data/base/tv-json/live/ZEE_CINEMA_USA.png",
            "imageFiller": "width-center",
            "action": "video:plugin:http://msx.benzac.de/plugins/hls.html?url=http://vo01.mohdtv.com:8880/live/voby5038/67747551/55209.m3u8"
        },
        {
            "type": "teaser",
            "color": "msx-white",
            "image": "https://infinitytechcmp.github.io/msx/data/base/tv-json/live/ZEE_MARATHI.png",
            "imageFiller": "width-center",
            "action": "video:plugin:http://msx.benzac.de/plugins/hls.html?url=http://vo01.mohdtv.com:8880/live/voby5038/67747551/55178.m3u8"
        },
        {
            "type": "teaser",
            "color": "msx-white",
            "image": "https://infinitytechcmp.github.io/msx/data/base/tv-json/live/ZEE_TV.png",
            "imageFiller": "width-center",
            "action": "video:plugin:http://msx.benzac.de/plugins/hls.html?url=http://vo01.mohdtv.com:8880/live/voby5038/67747551/54975.m3u8"
        }
    ]
}